AdversarialFriend/ActivationKernels.py
AdversarialFriend/CNN_feat_visualizer.py
AdversarialFriend/HeatmapVisualization.py
AdversarialFriend/LogisticRegression.py
AdversarialFriend/__init__.py
AdversarialFriend/cat.jpg
AdversarialFriend/catch_cat.py
AdversarialFriend/AttackMethod/Adversary.py
AdversarialFriend/AttackMethod/BasicIterativeAttack.py
AdversarialFriend/AttackMethod/CWAdversary.py
AdversarialFriend/AttackMethod/LLAdversary.py
AdversarialFriend/AttackMethod/__init__.py
adversarial_friend-1.1.8.dist-info/LICENSE
adversarial_friend-1.1.8.dist-info/METADATA
adversarial_friend-1.1.8.dist-info/WHEEL
adversarial_friend-1.1.8.dist-info/top_level.txt
adversarial_friend-1.1.8.dist-info/RECORD
