Metadata-Version: 2.1
Name: adversarial-friend
Version: 1.1.8
Summary: Group Project for CS 5523
Home-page: https://github.umn.edu/LI002252/CS_5523_Final_Project.git
Author: Adversarial_Friends Group
Author-email: li002252@umn.edu
Maintainer: Mario Serrafero, Jacob Isler 
Maintainer-email: isle0011@umn.edu, serra082@umn.edu
License: MIT
Platform: UNKNOWN
Classifier: License :: OSI Approved :: MIT License
Classifier: Programming Language :: Python
Classifier: Programming Language :: Python :: 3
Classifier: Programming Language :: Python :: 3.6
Classifier: Programming Language :: Python :: Implementation :: CPython
Classifier: Programming Language :: Python :: Implementation :: PyPy
Requires-Python: >=3.6.0
Requires-Dist: tensorflow (==2.3.0)
Requires-Dist: matplotlib (>=3.2.2)
Requires-Dist: numpy (>=1.18.5)
Requires-Dist: pandas (>=1.1.5)
Requires-Dist: Keras (==2.4.3)
Requires-Dist: importlib-resources (==3.3.0)
